flake8_no_debug_vars.py
flake8_no_debug_vars-0.1.0.dist-info/LICENSE
flake8_no_debug_vars-0.1.0.dist-info/METADATA
flake8_no_debug_vars-0.1.0.dist-info/WHEEL
flake8_no_debug_vars-0.1.0.dist-info/entry_points.txt
flake8_no_debug_vars-0.1.0.dist-info/top_level.txt
flake8_no_debug_vars-0.1.0.dist-info/RECORD
